pex/__init__.py
pex/__main__.py
pex/argparse.py
pex/artifact_url.py
pex/atexit.py
pex/atomic_directory.py
pex/attrs.py
pex/auth.py
pex/bootstrap.py
pex/build_properties.py
pex/cli_util.py
pex/common.py
pex/compatibility.py
pex/compiler.py
pex/dependency_configuration.py
pex/dependency_manager.py
pex/dist_metadata.py
pex/entry_points_txt.py
pex/enum.py
pex/environment.py
pex/exceptions.py
pex/executables.py
pex/executor.py
pex/fetcher.py
pex/finders.py
pex/fingerprinted_distribution.py
pex/globals.py
pex/hashing.py
pex/hashing.py.lck
pex/inherit_path.py
pex/installed_wheel.py
pex/interpreter.py
pex/interpreter_constraints.py
pex/interpreter_implementation.py
pex/interpreter_selection_strategy.py
pex/jobs.py
pex/lang.py
pex/layout.py
pex/namespace.py
pex/network_configuration.py
pex/orderedset.py
pex/os.py
pex/pep_376.py
pex/pep_425.py
pex/pep_427.py
pex/pep_440.py
pex/pep_503.py
pex/pep_508.py
pex/pep_723.py
pex/pex.py
pex/pex_boot.py
pex/pex_bootstrapper.py
pex/pex_builder.py
pex/pex_info.py
pex/pex_root.py
pex/pex_warnings.py
pex/platforms.py
pex/pth.py
pex/pyenv.py
pex/rank.py
pex/requirements.py
pex/resolver.py
pex/result.py
pex/sdist.py
pex/sh_boot.py
pex/sorted_tuple.py
pex/specifier_sets.py
pex/subprocess.py
pex/sysconfig.py
pex/targets.py
pex/toml.py
pex/tracer.py
pex/typing.py
pex/util.py
pex/variables.py
pex/version.py
pex/wheel.py
pex/whl.py
pex/ziputils.py
pex/bin/__init__.py
pex/bin/pex.py
pex/build_backend/__init__.py
pex/build_backend/configuration.py
pex/build_backend/pylock.py
pex/build_backend/wrap.py
pex/build_system/__init__.py
pex/build_system/pep_517.py
pex/build_system/pep_518.py
pex/cache/__init__.py
pex/cache/access.py
pex/cache/dirs.py
pex/cache/prunable.py
pex/cache/root.py
pex/cli/__init__.py
pex/cli/__main__.py
pex/cli/command.py
pex/cli/pex.py
pex/cli/commands/__init__.py
pex/cli/commands/cache_aware.py
pex/cli/commands/docs.py
pex/cli/commands/interpreter.py
pex/cli/commands/lock.py
pex/cli/commands/run.py
pex/cli/commands/scie.py
pex/vendor/_vendored/ansicolors/ansicolors-1.1.8.dist-info/DESCRIPTION.rst
pex/vendor/_vendored/ansicolors/ansicolors-1.1.8.dist-info/METADATA
pex/vendor/_vendored/ansicolors/ansicolors-1.1.8.dist-info/RECORD
pex/vendor/_vendored/ansicolors/ansicolors-1.1.8.dist-info/WHEEL
pex/vendor/_vendored/ansicolors/ansicolors-1.1.8.dist-info/metadata.json
pex/vendor/_vendored/ansicolors/ansicolors-1.1.8.dist-info/top_level.txt
pex/vendor/_vendored/ansicolors/ansicolors-1.1.8.pex-info/original-whl-info.json
pex/vendor/_vendored/appdirs/appdirs-1.4.4.dist-info/LICENSE.txt
pex/vendor/_vendored/appdirs/appdirs-1.4.4.dist-info/METADATA
pex/vendor/_vendored/appdirs/appdirs-1.4.4.dist-info/RECORD
pex/vendor/_vendored/appdirs/appdirs-1.4.4.dist-info/WHEEL
pex/vendor/_vendored/appdirs/appdirs-1.4.4.dist-info/top_level.txt
pex/vendor/_vendored/appdirs/appdirs-1.4.4.pex-info/original-whl-info.json
pex/vendor/_vendored/attrs/attrs-21.5.0.dev0.dist-info/AUTHORS.rst
pex/vendor/_vendored/attrs/attrs-21.5.0.dev0.dist-info/LICENSE
pex/vendor/_vendored/attrs/attrs-21.5.0.dev0.dist-info/METADATA
pex/vendor/_vendored/attrs/attrs-21.5.0.dev0.dist-info/RECORD
pex/vendor/_vendored/attrs/attrs-21.5.0.dev0.dist-info/WHEEL
pex/vendor/_vendored/attrs/attrs-21.5.0.dev0.dist-info/top_level.txt
pex/vendor/_vendored/attrs/attrs-21.5.0.dev0.pex-info/original-whl-info.json
pex/vendor/_vendored/packaging_20_9/packaging-20.9.dist-info/LICENSE
pex/vendor/_vendored/packaging_20_9/packaging-20.9.dist-info/LICENSE.APACHE
pex/vendor/_vendored/packaging_20_9/packaging-20.9.dist-info/LICENSE.BSD
pex/vendor/_vendored/packaging_20_9/packaging-20.9.dist-info/METADATA
pex/vendor/_vendored/packaging_20_9/packaging-20.9.dist-info/RECORD
pex/vendor/_vendored/packaging_20_9/packaging-20.9.dist-info/WHEEL
pex/vendor/_vendored/packaging_20_9/packaging-20.9.dist-info/top_level.txt
pex/vendor/_vendored/packaging_20_9/packaging-20.9.pex-info/original-whl-info.json
pex/vendor/_vendored/packaging_20_9/pyparsing-2.4.7.dist-info/LICENSE
pex/vendor/_vendored/packaging_20_9/pyparsing-2.4.7.dist-info/METADATA
pex/vendor/_vendored/packaging_20_9/pyparsing-2.4.7.dist-info/RECORD
pex/vendor/_vendored/packaging_20_9/pyparsing-2.4.7.dist-info/WHEEL
pex/vendor/_vendored/packaging_20_9/pyparsing-2.4.7.dist-info/top_level.txt
pex/vendor/_vendored/packaging_20_9/pyparsing-2.4.7.pex-info/original-whl-info.json
pex/vendor/_vendored/packaging_21_3/packaging-21.3.dist-info/LICENSE
pex/vendor/_vendored/packaging_21_3/packaging-21.3.dist-info/LICENSE.APACHE
pex/vendor/_vendored/packaging_21_3/packaging-21.3.dist-info/LICENSE.BSD
pex/vendor/_vendored/packaging_21_3/packaging-21.3.dist-info/METADATA
pex/vendor/_vendored/packaging_21_3/packaging-21.3.dist-info/RECORD
pex/vendor/_vendored/packaging_21_3/packaging-21.3.dist-info/WHEEL
pex/vendor/_vendored/packaging_21_3/packaging-21.3.dist-info/top_level.txt
pex/vendor/_vendored/packaging_21_3/packaging-21.3.pex-info/original-whl-info.json
pex/vendor/_vendored/packaging_21_3/pyparsing-3.0.7.dist-info/LICENSE
pex/vendor/_vendored/packaging_21_3/pyparsing-3.0.7.dist-info/METADATA
pex/vendor/_vendored/packaging_21_3/pyparsing-3.0.7.dist-info/RECORD
pex/vendor/_vendored/packaging_21_3/pyparsing-3.0.7.dist-info/WHEEL
pex/vendor/_vendored/packaging_21_3/pyparsing-3.0.7.dist-info/top_level.txt
pex/vendor/_vendored/packaging_21_3/pyparsing-3.0.7.pex-info/original-whl-info.json
pex/vendor/_vendored/packaging_24_0/packaging-24.0.dist-info/LICENSE
pex/vendor/_vendored/packaging_24_0/packaging-24.0.dist-info/LICENSE.APACHE
pex/vendor/_vendored/packaging_24_0/packaging-24.0.dist-info/LICENSE.BSD
pex/vendor/_vendored/packaging_24_0/packaging-24.0.dist-info/METADATA
pex/vendor/_vendored/packaging_24_0/packaging-24.0.dist-info/RECORD
pex/vendor/_vendored/packaging_24_0/packaging-24.0.dist-info/WHEEL
pex/vendor/_vendored/packaging_24_0/packaging-24.0.pex-info/original-whl-info.json
pex/vendor/_vendored/packaging_26_0/packaging-26.0.dist-info/METADATA
