Metadata-Version: 2.4
Name: pex
Version: 2.87.0
Summary: The PEX packaging toolchain.
Home-page: https://github.com/pex-tool/pex
Download-URL: https://github.com/pex-tool/pex/releases/download/v2.87.0/pex
Author: The PEX developers
Author-email: developers@pex-tool.org
License-Expression: Apache-2.0
Project-URL: Changelog, https://github.com/pex-tool/pex/blob/v2.87.0/CHANGES.md
Project-URL: Documentation, https://docs.pex-tool.org/
Project-URL: Source, https://github.com/pex-tool/pex/tree/v2.87.0
Keywords: package,executable,virtualenv,lock,freeze
Classifier: Development Status :: 5 - Production/Stable
Classifier: Intended Audience :: Developers
Classifier: Operating System :: Unix
Classifier: Operating System :: POSIX :: Linux
Classifier: Operating System :: MacOS :: MacOS X
Classifier: Programming Language :: Python
Classifier: Programming Language :: Python :: 2
Classifier: Programming Language :: Python :: 2.7
Classifier: Programming Language :: Python :: 3
Classifier: Programming Language :: Python :: 3.5
Classifier: Programming Language :: Python :: 3.6
Classifier: Programming Language :: Python :: 3.7
Classifier: Programming Language :: Python :: 3.8
Classifier: Programming Language :: Python :: 3.9
Classifier: Programming Language :: Python :: 3.10
Classifier: Programming Language :: Python :: 3.11
Classifier: Programming Language :: Python :: 3.12
Classifier: Programming Language :: Python :: 3.13
Classifier: Programming Language :: Python :: 3.14
Classifier: Programming Language :: Python :: 3.15
Classifier: Programming Language :: Python :: Implementation :: CPython
Classifier: Programming Language :: Python :: Implementation :: PyPy
Classifier: Topic :: Software Development :: Build Tools
Classifier: Topic :: System :: Archiving :: Packaging
Classifier: Topic :: System :: Software Distribution
Classifier: Topic :: Utilities
Requires-Python: !=3.0.*,!=3.1.*,!=3.2.*,!=3.3.*,!=3.4.*,<3.16,>=2.7
License-File: LICENSE
Provides-Extra: subprocess
Requires-Dist: subprocess32>=3.2.7; python_version < "3" and extra == "subprocess"
Provides-Extra: management
Requires-Dist: psutil>=5.3; extra == "management"
Dynamic: download-url
Dynamic: license-file
Dynamic: project-url
